{"currencies": [{"Last updated": "Tuesday 09 July 2024 06:05:07 PM", "US Dollar": "3.6725", "Argentine Peso": "0.004004", "Australian Dollar": "2.475731", "Bangladesh Taka": "0.031255", "Bahrani Dinar": "9.742155", "Brunei Dollar": "2.720975", "Brazilian Real": "0.675688", "Botswana Pula": "0.271029", "Belarus Rouble": "1.122196", "Canadian Dollar": "2.692844", "Swiss Franc": "4.09329", "Chilean Peso": "0.003931", "Chinese Yuan - Offshore": "0.503855", "Chinese Yuan": "0.505005", "Colombian Peso": "0.000911", "Czech Koruna": "0.157463", "Danish Krone": "0.532833", "Algerian Dinar": "0.027324", "Egypt Pound": "0.076399", "Euro": "3.973707", "GB Pound": "4.704714", "Hongkong Dollar": "0.470122", "Hungarian Forint": "0.010081", "Indonesia Rupiah": "0.000226", "Indian Rupee": "0.043991", "Iceland Krona": "0.026653", "Jordan Dinar": "5.179831", "Japanese Yen": "0.022798", "Kenya Shilling": "0.028635", "Korean Won": "0.002657", "Kuwaiti Dinar": "12.002418", "Kazakhstan Tenge": "0.007645", "Lebanon Pound": "0.000041", "Sri Lanka Rupee": "0.012081", "Moroccan Dirham": "0.372907", "Macedonia Denar": "0.064498", "Mexican Peso": "0.204759", "Malaysia Ringgit": "0.780138", "Nigerian Naira": "0.002393", "Norwegian Krone": "0.346825", "NewZealand Dollar": "2.249755", "Omani Rial": "9.538961", "Peru Sol": "0.970149", "Philippine Piso": "0.062838", "Pakistan Rupee": "0.013191", "Polish Zloty": "0.933338", "Qatari Riyal": "1.007103", "Serbian Dinar": "0.033948", "Russia Rouble": "0.041828", "Saudi Riyal": "0.979124", "Sudanese Pound": "0.006117", "Swedish Krona": "0.34816", "Singapore Dollar": "2.719565", "Thai Baht": "0.100921", "Tunisian Dinar": "1.172274", "Turkish Lira": "0.111668", "Trin Tob Dollar": "0.541204", "Taiwan Dollar": "0.112885", "Tanzania Shilling": "0.001383", "Uganda Shilling": "0.000991", "Vietnam Dong": "0.000144", "Yemen Rial": "0.014676", "South Africa Rand": "0.202391", "Zambian Kwacha": "0.146753", "Azerbaijan manat": "2.160294", "Bulgarian lev": "2.031138", "Croatian kuna": "0.521499", "Ethiopian birr": "0.06358", "Iraqi dinar": "0.002803", "Israeli new shekel": "1.00232", "Libyan dinar": "0.756733", "Mauritian rupee": "0.078539", "Romanian leu": "0.798752", "Syrian pound": "0.000282", "Turkmen manat": "1.049346", "Uzbekistani som": "0.000291"}]}