{"currencies": [{"Last updated": "Friday 12 January 2024 06:05:06 PM", "US Dollar": "3.6725", "Argentine Peso": "0.0045", "Australian Dollar": "2.462782", "Bangladesh Taka": "0.033462", "Bahrani Dinar": "9.740346", "Brunei Dollar": "2.759411", "Brazilian Real": "0.757591", "Botswana Pula": "0.27158", "Belarus Rouble": "1.122196", "Canadian Dollar": "2.749906", "Swiss Franc": "4.307413", "Chilean Peso": "0.004039", "Chinese Yuan - Offshore": "0.51154", "Chinese Yuan": "0.512382", "Colombian Peso": "0.000942", "Czech Koruna": "0.162889", "Danish Krone": "0.539518", "Algerian Dinar": "0.027287", "Egypt Pound": "0.118851", "Euro": "4.022894", "GB Pound": "4.684909", "Hongkong Dollar": "0.469533", "Hungarian Forint": "0.010612", "Indonesia Rupiah": "0.000236", "Indian Rupee": "0.044328", "Iceland Krona": "0.026809", "Jordan Dinar": "5.17691", "Japanese Yen": "0.02537", "Kenya Shilling": "0.023025", "Korean Won": "0.002802", "Kuwaiti Dinar": "11.953585", "Kazakhstan Tenge": "0.008136", "Lebanon Pound": "0.000244", "Sri Lanka Rupee": "0.0114", "Moroccan Dirham": "0.368792", "Macedonia Denar": "0.06537", "Mexican Peso": "0.21772", "Malaysia Ringgit": "0.79021", "Nigerian Naira": "0.003833", "Norwegian Krone": "0.357244", "NewZealand Dollar": "2.298041", "Omani Rial": "9.537722", "Peru Sol": "0.995554", "Philippine Piso": "0.065657", "Pakistan Rupee": "0.013246", "Polish Zloty": "0.923179", "Qatari Riyal": "1.006854", "Serbian Dinar": "0.034322", "Russia Rouble": "0.041542", "Saudi Riyal": "0.979647", "Sudanese Pound": "0.006117", "Swedish Krona": "0.357752", "Singapore Dollar": "2.760033", "Thai Baht": "0.104899", "Tunisian Dinar": "1.187819", "Turkish Lira": "0.122033", "Trin Tob Dollar": "0.541028", "Taiwan Dollar": "0.118045", "Tanzania Shilling": "0.00146", "Uganda Shilling": "0.000966", "Vietnam Dong": "0.00015", "Yemen Rial": "0.014678", "South Africa Rand": "0.197348", "Zambian Kwacha": "0.140574", "Azerbaijan manat": "2.160294", "Bulgarian lev": "2.058345", "Croatian kuna": "0.521499", "Ethiopian birr": "0.064937", "Iraqi dinar": "0.002803", "Israeli new shekel": "0.982556", "Libyan dinar": "0.765934", "Mauritian rupee": "0.083107", "Romanian leu": "0.809598", "Syrian pound": "0.000282", "Turkmen manat": "1.050787", "Uzbekistani som": "0.000297"}]}